django_htmlmin-0.10.0.dist-info/DESCRIPTION.rst
django_htmlmin-0.10.0.dist-info/METADATA
django_htmlmin-0.10.0.dist-info/RECORD
django_htmlmin-0.10.0.dist-info/WHEEL
django_htmlmin-0.10.0.dist-info/entry_points.txt
django_htmlmin-0.10.0.dist-info/metadata.json
django_htmlmin-0.10.0.dist-info/top_level.txt
htmlmin/__init__.py
htmlmin/commands.py
htmlmin/decorators.py
htmlmin/middleware.py
htmlmin/minify.py
htmlmin/util.py
htmlmin/tests/__init__.py
htmlmin/tests/mock_settings.py
htmlmin/tests/mock_settings_without_exclude.py
htmlmin/tests/mocks.py
htmlmin/tests/pico_django.py
htmlmin/tests/test_decorator.py
htmlmin/tests/test_middleware.py
htmlmin/tests/test_minify.py
htmlmin/tests/test_util.py
