Metadata-Version: 1.1
Name: django-htmlmin
Version: 0.10.0
Summary: HTML minifier for Python frameworks (not only Django, despite the name).
Home-page: UNKNOWN
Author: CobraTeam
Author-email: andrewsmedina@gmail.com
License: UNKNOWN
Keywords: django,html,minifier,minify
Platform: UNKNOWN
Classifier: Programming Language :: Python :: 2
Classifier: Development Status :: 5 - Production/Stable
Classifier: Framework :: Django :: 1.8
Classifier: Framework :: Django :: 1.9
Classifier: Framework :: Django
Classifier: Intended Audience :: Developers
Classifier: License :: OSI Approved :: BSD License
Classifier: Natural Language :: English
Classifier: Operating System :: OS Independent
Classifier: Programming Language :: Python :: 2.7
Classifier: Programming Language :: Python :: 3
Classifier: Programming Language :: Python :: 3.4
Classifier: Programming Language :: Python :: 3.5
Classifier: Topic :: Text Processing :: Markup :: HTML
